pbshipping
